nifverifier/__init__.py
nifverifier-0.0.1.dist-info/METADATA
nifverifier-0.0.1.dist-info/WHEEL
nifverifier-0.0.1.dist-info/top_level.txt
nifverifier-0.0.1.dist-info/RECORD
