Metadata-Version: 2.1
Name: nifverifier
Version: 0.0.1
Summary: Simple package to verify and generate NIF numbers in Portugal
Home-page: https://github.com/CharlieBrownCharacter/nifverifier
Author: Charlie Brown
Author-email: bruno11.francisco@gmail.com
License: UNKNOWN
Platform: UNKNOWN
Classifier: Programming Language :: Python :: 3
Classifier: License :: OSI Approved :: MIT License
Classifier: Operating System :: OS Independent
